DarkNews/AssignmentParser.py
DarkNews/Cfourvec.cpython-311-darwin.so
DarkNews/Cfourvec.pyx
DarkNews/GenLauncher.py
DarkNews/MC.py
DarkNews/ModelContainer.py
DarkNews/__init__.py
DarkNews/amplitudes.py
DarkNews/const.py
DarkNews/const_dics.py
DarkNews/decay_rates.py
DarkNews/detector.py
DarkNews/fourvec.py
DarkNews/geom.py
DarkNews/integrands.py
DarkNews/model.py
DarkNews/nuclear_tools.py
DarkNews/parsing_tools.py
DarkNews/pdg.py
DarkNews/phase_space.py
DarkNews/plot_tools.py
DarkNews/printer.py
DarkNews/processes.py
DarkNews/py.typed
DarkNews/scripts.py
DarkNews/include/assets/logo.png
DarkNews/include/assets/logo.svg
DarkNews/include/assets/logo_dark.png
DarkNews/include/assets/logo_dark.svg
DarkNews/include/aux_data/__init__.py
DarkNews/include/aux_data/alpha_QED_running_posQ2.dat
DarkNews/include/aux_data/mass20_1.txt
DarkNews/include/aux_data/mass20_rounded.txt
DarkNews/include/detectors/__init__.py
DarkNews/include/detectors/dune_nd_fhc.txt
DarkNews/include/detectors/dune_nd_rhc.txt
DarkNews/include/detectors/fasernu.txt
DarkNews/include/detectors/icarus.txt
DarkNews/include/detectors/icarus_dirt.txt
DarkNews/include/detectors/microboone.txt
DarkNews/include/detectors/microboone_dirt.txt
DarkNews/include/detectors/microboone_dirt_rectangular.txt
DarkNews/include/detectors/microboone_tpc.txt
DarkNews/include/detectors/minerva_le_fhc.txt
DarkNews/include/detectors/minerva_me_fhc.txt
DarkNews/include/detectors/minerva_me_rhc.txt
DarkNews/include/detectors/miniboone_fhc.txt
DarkNews/include/detectors/miniboone_fhc_dirt.txt
DarkNews/include/detectors/miniboone_rhc.txt
DarkNews/include/detectors/miniboone_rhc_dirt.txt
DarkNews/include/detectors/minos_le_fhc.txt
DarkNews/include/detectors/nd280_fhc.txt
DarkNews/include/detectors/nova_le_fhc.txt
DarkNews/include/detectors/nutev_fhc.txt
DarkNews/include/detectors/sbnd.txt
DarkNews/include/detectors/sbnd_dirt.txt
DarkNews/include/detectors/sbnd_dirt_cone.txt
DarkNews/include/fluxes/BNB_angle_energy_normalization.dat
darknews-0.4.8.dist-info/LICENSE
darknews-0.4.8.dist-info/METADATA
darknews-0.4.8.dist-info/WHEEL
darknews-0.4.8.dist-info/entry_points.txt
darknews-0.4.8.dist-info/top_level.txt
darknews-0.4.8.dist-info/RECORD
