Metadata-Version: 2.2
Name: DarkNews
Version: 0.4.8
Summary: A lightweight nu-A scattering generator for heavy neutral lepton production
Home-page: https://github.com/mhostert/DarkNews-generator
Author-email: "mhostert@g.harvard.edu"
License: "MIT"
Classifier: Programming Language :: Cython
Classifier: Programming Language :: Python :: 3
Classifier: Programming Language :: Python :: 3.8
Classifier: Programming Language :: Python :: 3.9
Classifier: Programming Language :: Python :: 3.10
Classifier: Programming Language :: Python :: 3.11
Classifier: Programming Language :: Python :: 3.12
Classifier: License :: OSI Approved :: MIT License
Classifier: Operating System :: OS Independent
Classifier: Intended Audience :: Science/Research
Classifier: Topic :: Scientific/Engineering
Requires-Python: >=3.8
License-File: LICENSE
Requires-Dist: dill
Requires-Dist: numpy
Requires-Dist: scipy
Requires-Dist: pandas>=1.0
Requires-Dist: vegas>=5.1.1
Requires-Dist: Particle
Requires-Dist: pyparsing
Requires-Dist: matplotlib
Provides-Extra: parquet
Requires-Dist: pyarrow; extra == "parquet"
Provides-Extra: pyhepmc
Requires-Dist: pyhepmc>=2.7.1; extra == "pyhepmc"
Provides-Extra: testing
Requires-Dist: pytest>=6.0; extra == "testing"
Requires-Dist: pytest-cov>=2.0; extra == "testing"
Requires-Dist: tox>=3.24; extra == "testing"
Requires-Dist: pyarrow; extra == "testing"
Requires-Dist: pyhepmc>=2.7.1; extra == "testing"
